divina/.DS_Store
divina/__init__.py
divina/datasets/__init__.py
divina/datasets/load.py
divina/datasets/datasets/retail_sales/_common_metadata
divina/datasets/datasets/retail_sales/_metadata
divina/datasets/datasets/retail_sales/part.0.parquet
divina/datasets/datasets/retail_sales/part.1.parquet
divina/datasets/datasets/retail_sales/part.2.parquet
divina/datasets/datasets/retail_sales/part.3.parquet
divina/datasets/datasets/retail_sales/part.4.parquet
divina/datasets/datasets/retail_sales/part.5.parquet
divina/datasets/raw/air_passengers/air_passengers.csv
divina/docs_src/__init__.py
divina/docs_src/conf.py
divina/docs_src/index.rst
divina/docs_src/orchestration.rst
divina/docs_src/quickstart.rst
divina/docs_src/scale.rst
divina/docs_src/_static/__init__.py
divina/docs_src/_static/css/docs.css
divina/docs_src/_static/examples/aws_example.py
divina/docs_src/_static/examples/base.py
divina/docs_src/_static/examples/local_artifact.py
divina/docs_src/_static/examples/prefect_example.py
divina/docs_src/_static/examples/s3_artifact.py
divina/docs_src/_static/js/docs.js
divina/docs_src/_static/pipeline_definitions/__init__.py
divina/docs_src/_static/pipeline_definitions/quickstart0.py
divina/docs_src/_static/pipeline_definitions/quickstart1.py
divina/docs_src/_static/pipeline_definitions/quickstart2.py
divina/docs_src/_static/pipeline_definitions/quickstart3.py
divina/docs_src/_static/pipeline_definitions/quickstart4.py
divina/docs_src/_static/pipeline_definitions/quickstart5.py
divina/docs_src/_static/pipeline_definitions/quickstart6.py
divina/docs_src/_static/pipeline_definitions/quickstart7.py
divina/docs_src/_static/pipeline_definitions/quickstart8.py
divina/pipeline/__init__.py
divina/pipeline/model.py
divina/pipeline/pipeline.py
divina/pipeline/utils.py
divina/tests/.DS_Store
divina/tests/__init__.py
divina/tests/conftest.py
divina/tests/test_1_unit.py
divina/tests/test_2_orchestration.py
divina/tests/test_3_integration.py
divina/tests/orchestration/Dockerfile
divina-2023.3.12.2.dist-info/LICENSE
divina-2023.3.12.2.dist-info/METADATA
divina-2023.3.12.2.dist-info/WHEEL
divina-2023.3.12.2.dist-info/pbr.json
divina-2023.3.12.2.dist-info/top_level.txt
divina-2023.3.12.2.dist-info/RECORD
