Metadata-Version: 2.1
Name: divina
Version: 2023.3.12.2
Summary: Package for causal, scalable forecasting
Home-page: https://www.coysu.com
Author: Coysu Consulting
Author-email: john@coysu.com
License: BSD-3-Clause
Project-URL: Bug Tracker, https://github.com/secrettoad/divina/issues
Project-URL: Documentation, https://secrettoad.github.io/divina/
Project-URL: Source Code, https://github.com/secrettoad/divina
Keywords: forecasting
Platform: UNKNOWN
Classifier: Development Status :: 3 - Alpha
Classifier: Environment :: Console
Classifier: Operating System :: OS Independent
Classifier: Programming Language :: Python
Classifier: Intended Audience :: Science/Research
Classifier: License :: OSI Approved :: BSD License
License-File: LICENSE
Requires-Dist: Sphinx (==6.1.3)
Requires-Dist: black (==22.12.0)
Requires-Dist: bokeh (==2.4.3)
Requires-Dist: dask-cloudprovider (==2022.10.0)
Requires-Dist: dask-ml (==2022.5.27)
Requires-Dist: dask (==2022.11.1)
Requires-Dist: dill (==0.3.6)
Requires-Dist: distributed (==2022.11.1)
Requires-Dist: flake8 (==6.0.0)
Requires-Dist: furo (==2022.12.7)
Requires-Dist: pandas (==1.5.2)
Requires-Dist: pbr (==5.11.1)
Requires-Dist: plotly (==5.11.0)
Requires-Dist: prefect (==2.8.5)
Requires-Dist: pyarrow (==10.0.1)
Requires-Dist: pytest (==7.2.0)
Requires-Dist: s3fs (==2022.11.0)
Requires-Dist: scikit-learn (==1.1.3)
Requires-Dist: sqlalchemy[asyncio] (!=1.4.33,<2.0,>=1.4.22)
Requires-Dist: twine (==4.0.2)
